LICENSE
MANIFEST.in
NOTICE
README.rst
THANKS
TODO.txt
bootstrap.py
buildout.cfg
requirements.txt
setup.cfg
setup.py
debian/changelog
debian/clean
debian/compat
debian/control
debian/copyright
debian/python-restkit.preinst
debian/pyversions
debian/rules
debian/watch
debian/source/format
doc/Makefile
doc/NOTICE
doc/api.rst
doc/authentication.rst
doc/client.rst
doc/conf.py
doc/ghp-import
doc/green.rst
doc/index.rst
doc/installation.rst
doc/make.bat
doc/news.rst
doc/pool.rst
doc/resource.rst
doc/shell.rst
doc/sitemap_config.xml
doc/sitemap_gen.py
doc/sphinxtogithub.py
doc/sphinxtogithub.pyc
doc/streaming.rst
doc/wsgi_proxy.rst
doc/_build/doctrees/api.doctree
doc/_build/doctrees/authentication.doctree
doc/_build/doctrees/client.doctree
doc/_build/doctrees/environment.pickle
doc/_build/doctrees/green.doctree
doc/_build/doctrees/index.doctree
doc/_build/doctrees/installation.doctree
doc/_build/doctrees/news.doctree
doc/_build/doctrees/pool.doctree
doc/_build/doctrees/resource.doctree
doc/_build/doctrees/shell.doctree
doc/_build/doctrees/streaming.doctree
doc/_build/doctrees/wsgi_proxy.doctree
doc/_build/doctrees/api/client.doctree
doc/_build/doctrees/api/conn.doctree
doc/_build/doctrees/api/datastructure.doctree
doc/_build/doctrees/api/errors.doctree
doc/_build/doctrees/api/filters.doctree
doc/_build/doctrees/api/forms.doctree
doc/_build/doctrees/api/modules.doctree
doc/_build/doctrees/api/oauth2.doctree
doc/_build/doctrees/api/resource.doctree
doc/_build/doctrees/api/restkit.contrib.doctree
doc/_build/doctrees/api/restkit.doctree
doc/_build/doctrees/api/session.doctree
doc/_build/doctrees/api/tee.doctree
doc/_build/doctrees/api/util.doctree
doc/_build/doctrees/api/version.doctree
doc/_build/doctrees/api/wrappers.doctree
doc/_build/html/.buildinfo
doc/_build/html/api.html
doc/_build/html/authentication.html
doc/_build/html/client.html
doc/_build/html/genindex.html
doc/_build/html/green.html
doc/_build/html/index.html
doc/_build/html/installation.html
restkit.egg-info/PKG-INFO
restkit.egg-info/SOURCES.txt
restkit.egg-info/dependency_links.txt
restkit.egg-info/entry_points.txt
restkit.egg-info/not-zip-safe
restkit.egg-info/requires.txt
restkit.egg-info/top_level.txt
