Metadata-Version: 1.0
Name: restkit
Version: 4.2.1
Summary: Python REST kit
Home-page: http://benoitc.github.com/restkit
Author: Benoit Chesneau
Author-email: benoitc@e-engura.org
License: MIT
Platform: UNKNOWN
Classifier: Development Status :: 4 - Beta
Classifier: Environment :: Web Environment
Classifier: Intended Audience :: Developers
Classifier: License :: OSI Approved :: MIT License
Classifier: Operating System :: OS Independent
Classifier: Programming Language :: Python
Classifier: Topic :: Internet :: WWW/HTTP
Classifier: Topic :: Software Development :: Libraries
